pyTTE/__init__.py
pyTTE/crystal_vectors.py
pyTTE/deformation.py
pyTTE/elastic_tensors.py
pyTTE/legacy.py
pyTTE/pyTTE.py
pyTTE/quantity.py
pyTTE/rotation_matrix.py
pyTTE/ttcrystal.py
pyTTE/ttscan.py
pyTTE-1.0.dist-info/LICENSE
pyTTE-1.0.dist-info/METADATA
pyTTE-1.0.dist-info/WHEEL
pyTTE-1.0.dist-info/top_level.txt
pyTTE-1.0.dist-info/RECORD
